py_distance_transforms/__init__.py
py_distance_transforms/julia_import.py
py_distance_transforms/juliapkg.json
py_distance_transforms/transform.py
py_distance_transforms/transform_cuda.py
py_distance_transforms-0.2.0.dist-info/METADATA
py_distance_transforms-0.2.0.dist-info/WHEEL
py_distance_transforms-0.2.0.dist-info/RECORD
