Metadata-Version: 2.3
Name: py_distance_transforms
Version: 0.2.0
Summary: Add your description here
Author-email: Dale Black <djblack@uci.edu>
Requires-Python: >=3.8
Requires-Dist: juliacall>=0.9.20
Requires-Dist: numpy>=1.25.0
Requires-Dist: torch>=2.2.0
